nonocaptcha_fork/__init__.py
nonocaptcha_fork/audio.py
nonocaptcha_fork/base.py
nonocaptcha_fork/exceptions.py
nonocaptcha_fork/image.py
nonocaptcha_fork/launcher.py
nonocaptcha_fork/nonocaptcha.example.yaml
nonocaptcha_fork/proxy.py
nonocaptcha_fork/solver.py
nonocaptcha_fork/speech.py
nonocaptcha_fork/util.py
nonocaptcha_fork/data/deface.html
nonocaptcha_fork/data/jquery.js
nonocaptcha_fork/data/override.js
nonocaptcha_fork-2.1.3.dist-info/LICENSE.rst
nonocaptcha_fork-2.1.3.dist-info/METADATA
nonocaptcha_fork-2.1.3.dist-info/WHEEL
nonocaptcha_fork-2.1.3.dist-info/top_level.txt
nonocaptcha_fork-2.1.3.dist-info/RECORD
