Metadata-Version: 2.1
Name: nonocaptcha-fork
Version: 2.1.3
Summary: An asynchronized Python library to automate solving ReCAPTCHA v2 by audio
Home-page: https://github.com/Francesco149/nonoCAPTCHA
Author: Michael Mooney <mikeyy@mikeyy.com>, Franc[e]sco <lolisamurai@tfwno.gf>
Author-email: mikeyy@mikeyy.com, lolisamurai@tfwno.gf
License: GPL-3.0
Platform: all
Classifier: Development Status :: 4 - Beta
Classifier: Intended Audience :: Developers
Classifier: Intended Audience :: Science/Research
Classifier: License :: OSI Approved :: GNU General Public License v3 (GPLv3)
Classifier: Natural Language :: English
Classifier: Operating System :: OS Independent
Classifier: Programming Language :: Python :: 3.6
Classifier: Programming Language :: Python :: 3.7
Classifier: Programming Language :: JavaScript
Classifier: Topic :: Scientific/Engineering
Classifier: Topic :: Software Development :: Libraries
Classifier: Topic :: Utilities
Requires-Dist: aiobotocore (==0.9.3)
Requires-Dist: aiofiles (==0.3.2)
Requires-Dist: aiohttp (==3.3.2)
Requires-Dist: async-timeout (==3.0.0)
Requires-Dist: peewee (==3.6.4)
Requires-Dist: pillow (==5.2.0)
Requires-Dist: pocketsphinx (==0.1.15)
Requires-Dist: psutil (==5.4.6)
Requires-Dist: pydub (==0.22.1)
Requires-Dist: pyppeteer-fork (>=0.0.28)
Requires-Dist: pyyaml (>=4.2b1)
Requires-Dist: requests (==2.20.0)
Requires-Dist: fuckcaptcha
Requires-Dist: websockets
Requires-Dist: flake8 (==3.5.0)
